dfviewer/__init__.py
dfviewer-0.0.2.dist-info/LICENSE
dfviewer-0.0.2.dist-info/METADATA
dfviewer-0.0.2.dist-info/WHEEL
dfviewer-0.0.2.dist-info/top_level.txt
dfviewer-0.0.2.dist-info/RECORD
