Metadata-Version: 2.1
Name: dfviewer
Version: 0.0.2
Summary: A data view tool for pandas data frames working on Jupyter Notebook or IPython.
Home-page: https://github.com/fatihmete/dfviewer
Author: Fatih Mete
Author-email: fatihmete@live.com
License: UNKNOWN
Platform: UNKNOWN
Classifier: Programming Language :: Python :: 3
Classifier: License :: OSI Approved :: MIT License
Classifier: Operating System :: OS Independent
Requires-Python: >=3.6
Requires-Dist: PyQt5
Requires-Dist: numpy
